tradestation/__init__.py
tradestation/client/__init__.py
tradestation/client/http_client.py
tradestation/client/tradestation_client.py
tradestation/services/Brokerage/__init__.py
tradestation/services/Brokerage/brokerage_service.py
tradestation/services/MarketData/__init__.py
tradestation/services/MarketData/market_data_service.py
tradestation/services/OrderExecution/__init__.py
tradestation/services/OrderExecution/order_execution_service.py
tradestation/services/__init__.py
tradestation/streaming/__init__.py
tradestation/streaming/stream_manager.py
tradestation/ts_types/__init__.py
tradestation/ts_types/brokerage.py
tradestation/ts_types/config.py
tradestation/ts_types/market_data.py
tradestation/ts_types/order_execution.py
tradestation/utils/__init__.py
tradestation/utils/exceptions.py
tradestation/utils/rate_limiter.py
tradestation/utils/stream_manager.py
tradestation/utils/token_manager.py
tradestation/utils/websocket_stream.py
tradestation_api_python-1.3.1.dist-info/METADATA
tradestation_api_python-1.3.1.dist-info/WHEEL
tradestation_api_python-1.3.1.dist-info/licenses/LICENSE
tradestation_api_python-1.3.1.dist-info/RECORD
