Metadata-Version: 2.4
Name: tradestation-api-python
Version: 1.3.1
Summary: A Python wrapper for the TradeStation WebAPI, providing easy access to brokerage, order execution, and market data services.
License: MIT
License-File: LICENSE
Author: mxcoppell
Requires-Python: >=3.11,<4.0
Classifier: License :: OSI Approved :: MIT License
Classifier: Programming Language :: Python :: 3
Classifier: Programming Language :: Python :: 3.11
Classifier: Programming Language :: Python :: 3.12
Classifier: Programming Language :: Python :: 3.13
Classifier: Programming Language :: Python :: 3.14
Requires-Dist: aiohttp (>=3.12.14,<4.0.0)
Requires-Dist: pydantic (>=2.10.6,<3.0.0)
Requires-Dist: python-dotenv (>=1.0.0,<2.0.0)
Requires-Dist: requests (>=2.32.4,<3.0.0)
Requires-Dist: urllib3 (>=2.6.0,<3.0.0)
Project-URL: Repository, https://github.com/mxcoppell/tradestation-api-python
